dash_discord/DiscordCrate.py
dash_discord/DiscordWidget.py
dash_discord/__init__.py
dash_discord/_imports_.py
dash_discord/dash_discord.min.js
dash_discord/dash_discord.min.js.map
dash_discord/metadata.json
dash_discord/package-info.json
dash_discord-0.0.3.dist-info/LICENSE
dash_discord-0.0.3.dist-info/METADATA
dash_discord-0.0.3.dist-info/WHEEL
dash_discord-0.0.3.dist-info/top_level.txt
dash_discord-0.0.3.dist-info/RECORD
