Metadata-Version: 2.1
Name: dash_discord
Version: 0.0.3
Summary: Discord Component for the Dash Framework
Author: Pip Install Python <pipinstallpython@gmail.com>
License: MIT
Classifier: Framework :: Dash
License-File: LICENSE
